lights/__init__.py
lights-0.2.0.dist-info/LICENSE
lights-0.2.0.dist-info/METADATA
lights-0.2.0.dist-info/WHEEL
lights-0.2.0.dist-info/entry_points.txt
lights-0.2.0.dist-info/top_level.txt
lights-0.2.0.dist-info/RECORD
